MANIFEST.in
README.rst
setup.cfg
setup.py
bin/ctt
ctt/__init__.py
ctt/ctt.py
ctt.egg-info/PKG-INFO
ctt.egg-info/SOURCES.txt
ctt.egg-info/dependency_links.txt
ctt.egg-info/requires.txt
ctt.egg-info/top_level.txt