Metadata-Version: 1.0
Name: ctt
Version: 0.0.2
Summary: Interface to CTT ( Portuguese Postal Service )
Home-page: https://github.com/bmartins/python-ctt
Author: Bruno Martins
Author-email: bscmartins@gmail.com
License: LICENSE
Platform: any
